cloud_vm_mcp_py-0.2.0.dist-info/licenses/LICENSE
vm_mcp/__init__.py
vm_mcp/config.py
vm_mcp/mcp.py
vm_mcp/model/__init__.py
vm_mcp/model/credentials.py
vm_mcp/model/vm.py
vm_mcp/providers/__init__.py
vm_mcp/providers/aws.py
vm_mcp/providers/azure.py
vm_mcp/providers/base.py
vm_mcp/providers/registry.py
cloud_vm_mcp_py-0.2.0.dist-info/METADATA
cloud_vm_mcp_py-0.2.0.dist-info/WHEEL
cloud_vm_mcp_py-0.2.0.dist-info/entry_points.txt
cloud_vm_mcp_py-0.2.0.dist-info/top_level.txt
cloud_vm_mcp_py-0.2.0.dist-info/RECORD
