Metadata-Version: 2.4
Name: cloud-vm-mcp-py
Version: 0.2.0
Summary: A Model Context Protocol for managing and viewing virtual machines across multiple cloud providers (AWS, Azure)
Author-email: Sean Dang <sondt.2709@gmail.com>
Maintainer-email: Sean Dang <sondt.2709@gmail.com>
License: MIT
Project-URL: Homepage, https://github.com/sondt2709/cloud-vm-mcp-py
Project-URL: Repository, https://github.com/sondt2709/cloud-vm-mcp-py
Keywords: vm,mcp,llm,automation,aws,azure,cloud
Requires-Python: >=3.10
License-File: LICENSE
Requires-Dist: mcp[cli]>=1.13.1
Requires-Dist: pydantic>=2.0.0
Requires-Dist: python-dotenv>=1.1.1
Requires-Dist: pyyaml>=6.0.0
Requires-Dist: watchdog>=4.0.0
Requires-Dist: boto3>=1.35.0
Requires-Dist: azure-identity>=1.17.0
Requires-Dist: azure-mgmt-compute>=32.0.0
Requires-Dist: azure-mgmt-network>=26.0.0
Dynamic: license-file
